grapharray/__init__.py
grapharray/classes.py
grapharray/functions.py
grapharray-1.0.2.dist-info/LICENSE
grapharray-1.0.2.dist-info/METADATA
grapharray-1.0.2.dist-info/WHEEL
grapharray-1.0.2.dist-info/top_level.txt
grapharray-1.0.2.dist-info/RECORD
